{
    "search-history": {
        "Kristján Jóhannsson (athlete)": "https://en.wikipedia.org/wiki/Special:Random",
        ".gif": "https://en.wikipedia.org/wiki/.gif",
        "bitmap": "https://en.wikipedia.org/wiki/Raster_graphics",
        "computer graphics": "https://en.wikipedia.org/wiki/Computer_graphics",
        "computer science": "https://en.wikipedia.org/wiki/Computer_science",
        "algorithmic processes": "https://en.wikipedia.org/wiki/Algorithm",
        "mathematics": "https://en.wikipedia.org/wiki/Mathematics",
        "quantity": "https://en.wikipedia.org/wiki/Quantity",
        "multitude": "https://en.wikipedia.org/wiki/Counting",
        "number": "https://en.wikipedia.org/wiki/Number",
        "mathematical object": "https://en.wikipedia.org/wiki/Mathematical_object",
        "abstract concept": "https://en.wikipedia.org/wiki/Abstract_concept",
        "abstract": "https://en.wikipedia.org/wiki/Abstraction",
        "rules": "https://en.wikipedia.org/wiki/Rule_of_inference",
        "logical form": "https://en.wikipedia.org/wiki/Logical_form",
        "philosophy": "https://en.wikipedia.org/wiki/Philosophy"
    },
    "target-link": "https://en.wikipedia.org/wiki/Philosophy",
    "crawl-final-state": "The target artice [Philosophy] is visited after 16 articles!"
}